smartrec_lib/__init__.py
smartrec_lib/model.py
smartrec_lib/save_and_load_triton_models.py
smartrec_lib/recommenders/__init__.py
smartrec_lib/recommenders/base.py
smartrec_lib/recommenders/recommender_als.py
smartrec_lib/recommenders/recommender_lightfm.py
smartrec_lib/recommenders/recommender_popular.py
smartrec_lib/recommenders/recommender_random.py
smartrec_lib/serving/config.pbtxt
smartrec_lib/serving/model.py
epoch8_smartrec_lib-0.1.0.dev1.dist-info/METADATA
epoch8_smartrec_lib-0.1.0.dev1.dist-info/WHEEL
epoch8_smartrec_lib-0.1.0.dev1.dist-info/RECORD
